docs/after.png
docs/before.png
docs/info_qrcode.png
xlfill2pdf/__init__.py
xlfill2pdf/core.py
xlfill2pdf/font.py
xlfill2pdf/fonts/default.ttf
xlfill2pdf/qrcode.py
xlfill2pdf-0.2.5.dist-info/LICENSE
xlfill2pdf-0.2.5.dist-info/METADATA
xlfill2pdf-0.2.5.dist-info/WHEEL
xlfill2pdf-0.2.5.dist-info/RECORD
