Metadata-Version: 2.1
Name: xlfill2pdf
Version: 0.2.5
Summary: Excel to PDF converter with font support
Home-page: https://github.com/xiwen-haochi/xlfill2pdf
License: MIT
Keywords: excel,pdf,converter
Author: 'fkl'
Author-email: 18654198191@163.com
Requires-Python: >=3.8,<4.0
Classifier: Development Status :: 4 - Beta
Classifier: Intended Audience :: Developers
Classifier: License :: OSI Approved :: MIT License
Classifier: Programming Language :: Python :: 3
Classifier: Programming Language :: Python :: 3.8
Classifier: Programming Language :: Python :: 3.9
Classifier: Programming Language :: Python :: 3.10
Classifier: Programming Language :: Python :: 3.11
Classifier: Programming Language :: Python :: 3.12
Classifier: Programming Language :: Python :: 3.13
Requires-Dist: openpyxl (>=3.0.9)
Requires-Dist: qrcode (>=7.0.0)
Requires-Dist: reportlab (>=4.2.2)
Requires-Dist: requests (>=2.22.0)
Project-URL: Repository, https://github.com/xiwen-haochi/xlfill2pdf
